bodosql/__init__.py
bodosql/compiler.py
bodosql/context.py
bodosql/context_ext.py
bodosql/ddl_ext.py
bodosql/imported_java_classes.py
bodosql/plan_conversion.py
bodosql/py4j_gateway.py
bodosql/remove_pure_calls.py
bodosql/runtests.py
bodosql/runtests_caching.py
bodosql/utils.py
bodosql/bodosql_types/__init__.py
bodosql/bodosql_types/database_catalog.py
bodosql/bodosql_types/database_catalog_ext.py
bodosql/bodosql_types/filesystem_catalog.py
bodosql/bodosql_types/filesystem_catalog_ext.py
bodosql/bodosql_types/glue_catalog.py
bodosql/bodosql_types/glue_catalog_ext.py
bodosql/bodosql_types/rest_catalog.py
bodosql/bodosql_types/rest_catalog_ext.py
bodosql/bodosql_types/s3_tables_catalog.py
bodosql/bodosql_types/s3_tables_catalog_ext.py
bodosql/bodosql_types/snowflake_catalog.py
bodosql/bodosql_types/snowflake_catalog_ext.py
bodosql/bodosql_types/table_path.py
bodosql/bodosql_types/table_path_ext.py
bodosql/jars/bodosql-executable.jar
bodosql/kernels/__init__.py
bodosql/kernels/array_kernel_utils.py
bodosql/kernels/casting_array_kernels.py
bodosql/kernels/comparison_array_kernels.py
bodosql/kernels/crypto_funcs.py
bodosql/kernels/datetime_array_kernels.py
bodosql/kernels/hash_array_kernels.py
bodosql/kernels/javascript_udf_array_kernels.py
bodosql/kernels/json_array_kernels.py
bodosql/kernels/lateral.py
bodosql/kernels/lead_lag.py
bodosql/kernels/like_array_kernels.py
bodosql/kernels/listagg.py
bodosql/kernels/nested_data_kernels.py
bodosql/kernels/numeric_array_kernels.py
bodosql/kernels/other_array_kernels.py
bodosql/kernels/parse_url_array_kernel.py
bodosql/kernels/regexp_array_kernels.py
bodosql/kernels/semi_structured_array_kernels.py
bodosql/kernels/snowflake_conversion_array_kernels.py
bodosql/kernels/special_handling_array_kernels.py
bodosql/kernels/string_array_kernels.py
bodosql/kernels/time_array_kernels.py
bodosql/kernels/trig_array_kernels.py
bodosql/kernels/variadic_array_kernels.py
bodosql/kernels/variant_array_kernels.py
bodosql-2026.1.dist-info/METADATA
bodosql-2026.1.dist-info/WHEEL
bodosql-2026.1.dist-info/top_level.txt
bodosql-2026.1.dist-info/RECORD
