Metadata-Version: 2.4
Name: bodosql
Version: 2026.1
Summary: Bodo's Vectorized SQL execution engine for clusters
Author: Bodo.ai
Project-URL: Homepage, https://bodo.ai
Project-URL: Documentation, https://docs.bodo.ai
Keywords: data,analytics,cluster
Classifier: Development Status :: 4 - Beta
Classifier: Intended Audience :: Developers
Classifier: Operating System :: POSIX :: Linux
Classifier: Operating System :: MacOS :: MacOS X
Classifier: Programming Language :: Python
Classifier: Programming Language :: Python :: 3.10
Classifier: Programming Language :: Python :: 3.11
Classifier: Programming Language :: Python :: 3.12
Classifier: Programming Language :: Python :: 3.13
Classifier: Programming Language :: Python :: 3.14
Classifier: Topic :: Software Development :: Compilers
Classifier: Topic :: System :: Distributed Computing
Requires-Python: >=3.10
Requires-Dist: py4j==0.10.9.9
